MANIFEST.in
README.rst
setup.py
epigen/__init__.py
epigen.egg-info/PKG-INFO
epigen.egg-info/SOURCES.txt
epigen.egg-info/dependency_links.txt
epigen.egg-info/entry_points.txt
epigen.egg-info/requires.txt
epigen.egg-info/top_level.txt
epigen/commands/__init__.py
epigen/commands/command.py
epigen/commands/pair/__init__.py
epigen/commands/pair/cmd_all.py
epigen/commands/pair/cmd_mixed.py
epigen/commands/pair/cmd_random.py
epigen/commands/pair/cmd_single.py
epigen/commands/pheno/__init__.py
epigen/commands/pheno/cmd_additive.py
epigen/commands/pheno/cmd_binary.py
epigen/commands/pheno/cmd_cont.py
epigen/commands/pheno/cmd_env.py
epigen/interaction/__init__.py
epigen/interaction/generator.py
epigen/interaction/util.py
epigen/plink/__init__.py
epigen/plink/case.py
epigen/plink/cov.py
epigen/plink/generate.py
epigen/plink/model.py
epigen/plink/output.py
epigen/plink/pair.py
epigen/plink/pairs.py
epigen/plink/plink_file.py
epigen/plink/util.py
epigen/tools/__init__.py
epigen/tools/run_epigen.py