Metadata-Version: 1.1
Name: epigen
Version: 0.3.0
Summary: A tool for genetic data under epistatic models
Home-page: https://github.com/fadern/epigen
Author: Mattias Franberg
Author-email: mattias.franberg@scilifelab.se
License: BSD
Keywords: epigen bioinformatics genetics
Platform: UNKNOWN
Classifier: Development Status :: 3 - Alpha
Classifier: Intended Audience :: Science/Research
Classifier: Topic :: Scientific/Engineering :: Bio-Informatics
Classifier: License :: OSI Approved :: BSD License
Classifier: Programming Language :: Python :: 2
Classifier: Programming Language :: Python :: 2.6
Classifier: Programming Language :: Python :: 2.7
Classifier: Programming Language :: Python :: 3
Classifier: Programming Language :: Python :: 3.2
Classifier: Programming Language :: Python :: 3.3
Classifier: Programming Language :: Python :: 3.4
